{"cameraMode":{"drawMode":0,"name":"Shaded","section":"Shading Mode"},"sceneLighting":true,"audioPlay":false,"sceneViewState":{"m_AlwaysRefresh":false,"showFog":true,"showSkybox":true,"showFlares":true,"showImageEffects":true,"showParticleSystems":true,"showVisualEffectGraphs":true,"m_FxEnabled":true},"in2DMode":false,"pivot":{"x":0.0,"y":13.199999809265137,"z":0.0},"rotation":{"x":-0.4540306627750397,"y":0.09553892910480499,"z":-0.048537060618400577,"w":-0.8849350810050964},"size":23.582595825195314,"orthographic":true}